boas-1.7.data/scripts/boas
src/__init__.py
src/locators.py
src/page.py
src/parser.py
src/runner.py
src/boas/__init__.py
src/boas/locators.py
src/boas/page.py
src/boas/parser.py
src/boas/runner.py
boas-1.7.dist-info/LICENSE
boas-1.7.dist-info/METADATA
boas-1.7.dist-info/WHEEL
boas-1.7.dist-info/top_level.txt
boas-1.7.dist-info/RECORD
