Metadata-Version: 2.1
Name: boas
Version: 1.7
Summary: Bank of America personal financial web scraper
Home-page: https://github.com/eshaffer321/BankofAmerica-Web-Scraper
Author: Erick Shaffer
Author-email: erick.shaffer321@gmail.com
License: UNKNOWN
Keywords: bankofamerica,python,boa,web scraper,selenium,screen scraper,data
Platform: UNKNOWN
Classifier: License :: OSI Approved :: MIT License
Classifier: Operating System :: OS Independent
Requires-Dist: knack
